{"items":[{"category":"Neuroimaging & Brain Computing","homepage_url":"https://www.fil.ion.ucl.ac.uk/spm/","id":"neuroimaging-brain-computing--neuroimaging-platforms--spm","logo":"","name":"SPM","subcategory":"Neuroimaging Platforms","website":"https://www.fil.ion.ucl.ac.uk/spm/","description":"Statistical Parametric Mapping","featured":{"label":"Graduated","order":1},"maturity":"graduated"},{"category":"Neuroimaging & Brain Computing","homepage_url":"https://surfer.nmr.mgh.harvard.edu/","id":"neuroimaging-brain-computing--neuroimaging-platforms--freesurfer","logo":"","name":"FreeSurfer","subcategory":"Neuroimaging Platforms","website":"https://surfer.nmr.mgh.harvard.edu/","description":"Brain surface analysis","featured":{"label":"Graduated","order":1},"maturity":"graduated"},{"category":"Neuroimaging & Brain Computing","homepage_url":"https://www.mimsoftware.com/nuclear-medicine/mim-neuro","id":"neuroimaging-brain-computing--neuroimaging-platforms--mimneuro","logo":"","name":"MIMneuro","subcategory":"Neuroimaging Platforms","website":"https://www.mimsoftware.com/nuclear-medicine/mim-neuro","description":"Statistical Parametric Mapping software","featured":{"label":"Graduated","order":1},"maturity":"graduated"},{"category":"Neuroimaging & Brain Computing","homepage_url":"https://www.thermofisher.com/us/en/home/electron-microscopy/products/software-em-3d-vis/amira-software.html","id":"neuroimaging-brain-computing--neuroimaging-platforms--amira","logo":"","name":"Amira","subcategory":"Neuroimaging Platforms","website":"https://www.thermofisher.com/us/en/home/electron-microscopy/products/software-em-3d-vis/amira-software.html","description":"Statistical Parametric Mapping","featured":{"label":"Graduated","order":1},"maturity":"graduated"},{"category":"Neuroimaging & Brain Computing","homepage_url":"https://neurodesk.org/","id":"neuroimaging-brain-computing--comprehensive-platforms--neurodesk","logo":"","name":"Neurodesk","subcategory":"Comprehensive Platforms","website":"https://neurodesk.org/","description":"Complete neuroimaging suite","featured":{"label":"Graduated","order":1},"maturity":"graduated"},{"category":"Neuroimaging & Brain Computing","homepage_url":"https://brainforge.rs.gsu.edu/","id":"neuroimaging-brain-computing--comprehensive-platforms--brainforge","logo":"","name":"BrainForge","subcategory":"Comprehensive Platforms","website":"https://brainforge.rs.gsu.edu/","description":"Brain imaging and analysis platform","featured":{"label":"Graduated","order":1},"maturity":"graduated"},{"category":"Neuroimaging & Brain Computing","homepage_url":"https://neuroconductor.org/","id":"neuroimaging-brain-computing--comprehensive-platforms--neuroconductor","logo":"","name":"Neuroconductor","subcategory":"Comprehensive Platforms","website":"https://neuroconductor.org/","description":"Bioinformatics tools for R","featured":{"label":"Graduated","order":1},"maturity":"graduated"},{"category":"Neuroimaging & Brain Computing","homepage_url":"https://openbci.com/","id":"neuroimaging-brain-computing--brain-computer-interface--openbci","logo":"","name":"OpenBCI","subcategory":"Brain-Computer Interface","website":"https://openbci.com/","description":"Open-source brain-computer interface hardware","featured":{"label":"Graduated","order":1},"maturity":"graduated"},{"category":"Neuroimaging & Brain Computing","homepage_url":"https://store.neurosky.com/","id":"neuroimaging-brain-computing--brain-computer-interface--neurosky","logo":"","name":"NeuroSky","subcategory":"Brain-Computer Interface","website":"https://store.neurosky.com/","description":"EEG-based neurotechnology and sensors","featured":{"label":"Graduated","order":1},"maturity":"graduated"},{"category":"Neuroimaging & Brain Computing","homepage_url":"https://www.nitrc.org/","id":"neuroimaging-brain-computing--reference-resources--nitrc","logo":"","name":"NITRC","subcategory":"Reference & Resources","website":"https://www.nitrc.org/","description":"Neuroimaging Informatics Tools and Resources","featured":{"label":"Graduated","order":1},"maturity":"graduated"}]}